aws_ecs_services/__init__.py
aws_ecs_services/_version.py
aws_ecs_services/arguments.py
aws_ecs_services/aws_ecs_services.py
aws_ecs_services/environment_defaults.py
aws_ecs_services/force_restart_services.py
aws_ecs_services-1.0.2.data/scripts/aws-ecs-services
aws_ecs_services-1.0.2.data/scripts/aws_ecs_services
aws_ecs_services-1.0.2.dist-info/METADATA
aws_ecs_services-1.0.2.dist-info/WHEEL
aws_ecs_services-1.0.2.dist-info/top_level.txt
aws_ecs_services-1.0.2.dist-info/RECORD
