Metadata-Version: 2.1
Name: aws-ecs-services
Version: 1.0.2
Summary: Get ECS service info (e.g. EC2 instance id) by a given service name.
Home-page: https://github.com/normoes/aws_ecs_services
Author: Norman Moeschter-Schenck
Author-email: norman.moeschter@gmail.com
License: UNKNOWN
Download-URL: https://github.com/normoes/aws_ecs_services/archive/v1.0.2.tar.gz
Platform: UNKNOWN
Classifier: Development Status :: 5 - Production/Stable
Classifier: Intended Audience :: Developers
Classifier: License :: OSI Approved :: MIT License
Classifier: Natural Language :: English
Classifier: Programming Language :: Python
Requires-Dist: boto3 (>=1.14.4)
